[{"NO":"1","NO_PBP":"49111937344","KOTA":"KAB. PEMALANG","KECAMATAN":"BODEH","DESA":"KEBANDUNGAN","NAMA":"AAS WILANTIKA","NAMA_PENERIMA":"AAS WILANTIKA","NIK":"3217075506960019","NIK_PENERIMA":"3217075506960019","PEKERJAAN":"","FOTO_URL":"2PBP_49111937344.jpg","STATUS":"AWAL","RT":0,"RW":0,"TANGGAL":""},{"NO":"2","NO_PBP":"49111937211","KOTA":"KAB. PEMALANG","KECAMATAN":"BODEH","DESA":"KEBANDUNGAN","NAMA":"ABDUL GHOPAR","NAMA_PENERIMA":"RISNAWATI","NIK":"3327052006920004","NIK_PENERIMA":"3327055208950003","PEKERJAAN":"","FOTO_URL":"2PBP_49111937211.jpg","STATUS":"AWAL","RT":1,"RW":1,"TANGGAL":""},{"NO":"3","NO_PBP":"49111937213","KOTA":"KAB. PEMALANG","KECAMATAN":"BODEH","DESA":"KEBANDUNGAN","NAMA":"ADE PURHAN","NAMA_PENERIMA":"ADE PURHAN","NIK":"3327052706790005","NIK_PENERIMA":"3327052706790005","PEKERJAAN":"","FOTO_URL":"2PBP_49111937213.jpg","STATUS":"AWAL","RT":2,"RW":1,"TANGGAL":""},{"NO":"4","NO_PBP":"49111937214","KOTA":"KAB. PEMALANG","KECAMATAN":"BODEH","DESA":"KEBANDUNGAN","NAMA":"AISAH","NAMA_PENERIMA":"AISAH","NIK":"3327052505780003","NIK_PENERIMA":"3327052505780003","PEKERJAAN":"","FOTO_URL":"2PBP_49111937214.jpg","STATUS":"AWAL","RT":2,"RW":1,"TANGGAL":""},{"NO":"5","NO_PBP":"49111937216","KOTA":"KAB. PEMALANG","KECAMATAN":"BODEH","DESA":"KEBANDUNGAN","NAMA":"AL KONI","NAMA_PENERIMA":"AL KONI","NIK":"3327050604820004","NIK_PENERIMA":"3327050604820004","PEKERJAAN":"","FOTO_URL":"2PBP_49111937216.jpg","STATUS":"AWAL","RT":1,"RW":2,"TANGGAL":""},{"NO":"6","NO_PBP":"49111937217","KOTA":"KAB. PEMALANG","KECAMATAN":"BODEH","DESA":"KEBANDUNGAN","NAMA":"ALI MURSALIM","NAMA_PENERIMA":"KUSNAENI","NIK":"3327050603860005","NIK_PENERIMA":"3327055706790004","PEKERJAAN":"","FOTO_URL":"2PBP_49111937217.jpg","STATUS":"AWAL","RT":3,"RW":2,"TANGGAL":""},{"NO":"7","NO_PBP":"49111937218","KOTA":"KAB. PEMALANG","KECAMATAN":"BODEH","DESA":"KEBANDUNGAN","NAMA":"ALI MURTADO","NAMA_PENERIMA":"MELANI","NIK":"3327053001870003","NIK_PENERIMA":"3327054303940001","PEKERJAAN":"","FOTO_URL":"2PBP_49111937218.jpg","STATUS":"AWAL","RT":3,"RW":2,"TANGGAL":""},{"NO":"8","NO_PBP":"49111937219","KOTA":"KAB. PEMALANG","KECAMATAN":"BODEH","DESA":"KEBANDUNGAN","NAMA":"AMIR","NAMA_PENERIMA":"AMIR","NIK":"3327050107860079","NIK_PENERIMA":"3327050107860079","PEKERJAAN":"","FOTO_URL":"2PBP_49111937219.jpg","STATUS":"AWAL","RT":1,"RW":2,"TANGGAL":""},{"NO":"9","NO_PBP":"49111937222","KOTA":"KAB. PEMALANG","KECAMATAN":"BODEH","DESA":"KEBANDUNGAN","NAMA":"BADRIYAH","NAMA_PENERIMA":"BADRIYAH","NIK":"3327055703630001","NIK_PENERIMA":"3327055703630001","PEKERJAAN":"","FOTO_URL":"2PBP_49111937222.jpg","STATUS":"AWAL","RT":0,"RW":0,"TANGGAL":""},{"NO":"10","NO_PBP":"49111937221","KOTA":"KAB. PEMALANG","KECAMATAN":"BODEH","DESA":"KEBANDUNGAN","NAMA":"BUDI HARTO","NAMA_PENERIMA":"BUDI HARTO","NIK":"3275011203810038","NIK_PENERIMA":"3275011203810038","PEKERJAAN":"","FOTO_URL":"2PBP_49111937221.jpg","STATUS":"AWAL","RT":3,"RW":3,"TANGGAL":""},{"NO":"11","NO_PBP":"49111937223","KOTA":"KAB. PEMALANG","KECAMATAN":"BODEH","DESA":"KEBANDUNGAN","NAMA":"CARMI","NAMA_PENERIMA":"CARMI","NIK":"3327050204730004","NIK_PENERIMA":"3327050204730004","PEKERJAAN":"","FOTO_URL":"2PBP_49111937223.jpg","STATUS":"AWAL","RT":3,"RW":2,"TANGGAL":""},{"NO":"12","NO_PBP":"49111937225","KOTA":"KAB. PEMALANG","KECAMATAN":"BODEH","DESA":"KEBANDUNGAN","NAMA":"CASMINAH","NAMA_PENERIMA":"CASMINAH","NIK":"3327054504600001","NIK_PENERIMA":"3327054504600001","PEKERJAAN":"","FOTO_URL":"2PBP_49111937225.jpg","STATUS":"AWAL","RT":1,"RW":2,"TANGGAL":""},{"NO":"13","NO_PBP":"49111937227","KOTA":"KAB. PEMALANG","KECAMATAN":"BODEH","DESA":"KEBANDUNGAN","NAMA":"CATUR CAHYADI TIO","NAMA_PENERIMA":"CATUR CAHYADI TIO","NIK":"3326092702960001","NIK_PENERIMA":"3326092702960001","PEKERJAAN":"","FOTO_URL":"2PBP_49111937227.jpg","STATUS":"AWAL","RT":3,"RW":2,"TANGGAL":""},{"NO":"14","NO_PBP":"49111937228","KOTA":"KAB. PEMALANG","KECAMATAN":"BODEH","DESA":"KEBANDUNGAN","NAMA":"CISWANTO","NAMA_PENERIMA":"CISWANTO","NIK":"3326110810900001","NIK_PENERIMA":"3326110810900001","PEKERJAAN":"","FOTO_URL":"2PBP_49111937228.jpg","STATUS":"AWAL","RT":1,"RW":1,"TANGGAL":""},{"NO":"15","NO_PBP":"49111937229","KOTA":"KAB. PEMALANG","KECAMATAN":"BODEH","DESA":"KEBANDUNGAN","NAMA":"DALAM","NAMA_PENERIMA":"SITI MUPIYAH","NIK":"3327053110480001","NIK_PENERIMA":"3327056910560003","PEKERJAAN":"","FOTO_URL":"2PBP_49111937229.jpg","STATUS":"AWAL","RT":1,"RW":1,"TANGGAL":""},{"NO":"16","NO_PBP":"49111937230","KOTA":"KAB. PEMALANG","KECAMATAN":"BODEH","DESA":"KEBANDUNGAN","NAMA":"DANOTO","NAMA_PENERIMA":"DANOTO","NIK":"3326091506880001","NIK_PENERIMA":"3326091506880001","PEKERJAAN":"","FOTO_URL":"2PBP_49111937230.jpg","STATUS":"AWAL","RT":3,"RW":3,"TANGGAL":""},{"NO":"17","NO_PBP":"49111937231","KOTA":"KAB. PEMALANG","KECAMATAN":"BODEH","DESA":"KEBANDUNGAN","NAMA":"DARMINTO","NAMA_PENERIMA":"NURSADITRI","NIK":"3326081211970001","NIK_PENERIMA":"3327057101980002","PEKERJAAN":"","FOTO_URL":"2PBP_49111937231.jpg","STATUS":"PERWAKILAN","RT_PENERIMA":"003","RW_PENERIMA":"002","ALASAN":"Bekerja","RT":3,"RW":2,"TANGGAL":""},{"NO":"18","NO_PBP":"49111937232","KOTA":"KAB. PEMALANG","KECAMATAN":"BODEH","DESA":"KEBANDUNGAN","NAMA":"DAROJI","NAMA_PENERIMA":"DAROJI","NIK":"3327051309860007","NIK_PENERIMA":"3327051309860007","PEKERJAAN":"","FOTO_URL":"2PBP_49111937232.jpg","STATUS":"AWAL","RT":1,"RW":2,"TANGGAL":""},{"NO":"19","NO_PBP":"49111937248","KOTA":"KAB. PEMALANG","KECAMATAN":"BODEH","DESA":"KEBANDUNGAN","NAMA":"DARSINAH","NAMA_PENERIMA":"ANGGITA FEBRILIAN","NIK":"3327054312720002","NIK_PENERIMA":"3327055002070001","PEKERJAAN":"","FOTO_URL":"2PBP_49111937248.jpg","STATUS":"AWAL","RT":0,"RW":0,"TANGGAL":""},{"NO":"20","NO_PBP":"49111937233","KOTA":"KAB. PEMALANG","KECAMATAN":"BODEH","DESA":"KEBANDUNGAN","NAMA":"DARYANTO","NAMA_PENERIMA":"DARYANTO","NIK":"3327052803800004","NIK_PENERIMA":"3327052803800004","PEKERJAAN":"","FOTO_URL":"2PBP_49111937233.jpg","STATUS":"AWAL","RT":1,"RW":2,"TANGGAL":""},{"NO":"21","NO_PBP":"49111937235","KOTA":"KAB. PEMALANG","KECAMATAN":"BODEH","DESA":"KEBANDUNGAN","NAMA":"DARYONO","NAMA_PENERIMA":"DARYONO","NIK":"3327052303640002","NIK_PENERIMA":"3327052303640002","PEKERJAAN":"","FOTO_URL":"2PBP_49111937235.jpg","STATUS":"AWAL","RT":3,"RW":2,"TANGGAL":""},{"NO":"22","NO_PBP":"49111937234","KOTA":"KAB. PEMALANG","KECAMATAN":"BODEH","DESA":"KEBANDUNGAN","NAMA":"DARYONO","NAMA_PENERIMA":"SUKARTI","NIK":"3327052009570001","NIK_PENERIMA":"3327054107620046","PEKERJAAN":"","FOTO_URL":"2PBP_49111937234.jpg","STATUS":"AWAL","RT":1,"RW":2,"TANGGAL":""},{"NO":"23","NO_PBP":"49111937237","KOTA":"KAB. PEMALANG","KECAMATAN":"BODEH","DESA":"KEBANDUNGAN","NAMA":"DEWI AYU WULANDARI","NAMA_PENERIMA":"DEWI AYU WULANDARI","NIK":"3175022809640009","NIK_PENERIMA":"3175022809640009","PEKERJAAN":"","FOTO_URL":"2PBP_49111937237.jpg","STATUS":"AWAL","RT":3,"RW":2,"TANGGAL":""},{"NO":"24","NO_PBP":"49111937238","KOTA":"KAB. PEMALANG","KECAMATAN":"BODEH","DESA":"KEBANDUNGAN","NAMA":"DODO SUBADRI","NAMA_PENERIMA":"DODO SUBADRI","NIK":"3216022509750008","NIK_PENERIMA":"3216022509750008","PEKERJAAN":"","FOTO_URL":"2PBP_49111937238.jpg","STATUS":"AWAL","RT":1,"RW":3,"TANGGAL":""},{"NO":"25","NO_PBP":"49111937239","KOTA":"KAB. PEMALANG","KECAMATAN":"BODEH","DESA":"KEBANDUNGAN","NAMA":"DWI PURNOMO","NAMA_PENERIMA":"WINARSIH","NIK":"3327050705820004","NIK_PENERIMA":"3327056809850005","PEKERJAAN":"","FOTO_URL":"2PBP_49111937239.jpg","STATUS":"AWAL","RT":3,"RW":2,"TANGGAL":""},{"NO":"26","NO_PBP":"49111937240","KOTA":"KAB. PEMALANG","KECAMATAN":"BODEH","DESA":"KEBANDUNGAN","NAMA":"EDI KUSNADI","NAMA_PENERIMA":"MAPTUKHAH","NIK":"3327102106840121","NIK_PENERIMA":"3327056206880002","PEKERJAAN":"","FOTO_URL":"2PBP_49111937240.jpg","STATUS":"AWAL","RT":2,"RW":2,"TANGGAL":""},{"NO":"27","NO_PBP":"49111937242","KOTA":"KAB. PEMALANG","KECAMATAN":"BODEH","DESA":"KEBANDUNGAN","NAMA":"EKO WINOTO","NAMA_PENERIMA":"EKO WINOTO","NIK":"3327053101750001","NIK_PENERIMA":"3327053101750001","PEKERJAAN":"","FOTO_URL":"2PBP_49111937242.jpg","STATUS":"AWAL","RT":1,"RW":2,"TANGGAL":""},{"NO":"28","NO_PBP":"49111937267","KOTA":"KAB. PEMALANG","KECAMATAN":"BODEH","DESA":"KEBANDUNGAN","NAMA":"ELISAH","NAMA_PENERIMA":"ELISAH","NIK":"3327055009930001","NIK_PENERIMA":"3327055009930001","PEKERJAAN":"","FOTO_URL":"2PBP_49111937267.jpg","STATUS":"AWAL","RT":0,"RW":0,"TANGGAL":""},{"NO":"29","NO_PBP":"49111937304","KOTA":"KAB. PEMALANG","KECAMATAN":"BODEH","DESA":"KEBANDUNGAN","NAMA":"EVI ASTUTI","NAMA_PENERIMA":"EVI ASTUTI","NIK":"3327055308870001","NIK_PENERIMA":"3327055308870001","PEKERJAAN":"","FOTO_URL":"2PBP_49111937304.jpg","STATUS":"AWAL","RT":0,"RW":0,"TANGGAL":""},{"NO":"30","NO_PBP":"49111937376","KOTA":"KAB. PEMALANG","KECAMATAN":"BODEH","DESA":"KEBANDUNGAN","NAMA":"FARDIYATUT DINIYAH","NAMA_PENERIMA":"FARDIYATUT DINIYAH","NIK":"3327056212940001","NIK_PENERIMA":"3327056212940001","PEKERJAAN":"","FOTO_URL":"2PBP_49111937376.jpg","STATUS":"AWAL","RT":0,"RW":0,"TANGGAL":""},{"NO":"31","NO_PBP":"49111937244","KOTA":"KAB. PEMALANG","KECAMATAN":"BODEH","DESA":"KEBANDUNGAN","NAMA":"GUNAWAN","NAMA_PENERIMA":"SOHIRIN","NIK":"3327052711820002","NIK_PENERIMA":"3327050205680003","PEKERJAAN":"","FOTO_URL":"2PBP_49111937244.jpg","STATUS":"PERWAKILAN","RT_PENERIMA":"001","RW_PENERIMA":"002","ALASAN":"Bekerja","RT":3,"RW":2,"TANGGAL":""},{"NO":"32","NO_PBP":"49111937243","KOTA":"KAB. PEMALANG","KECAMATAN":"BODEH","DESA":"KEBANDUNGAN","NAMA":"GUNTORO","NAMA_PENERIMA":"GUNTORO","NIK":"3328140407910005","NIK_PENERIMA":"3328140407910005","PEKERJAAN":"","FOTO_URL":"2PBP_49111937243.jpg","STATUS":"AWAL","RT":0,"RW":0,"TANGGAL":""},{"NO":"33","NO_PBP":"49111937245","KOTA":"KAB. PEMALANG","KECAMATAN":"BODEH","DESA":"KEBANDUNGAN","NAMA":"GUNTORO","NAMA_PENERIMA":"DUMI MARIFAH","NIK":"3327052204790003","NIK_PENERIMA":"3327055506900005","PEKERJAAN":"","FOTO_URL":"2PBP_49111937245.jpg","STATUS":"AWAL","RT":3,"RW":2,"TANGGAL":""},{"NO":"34","NO_PBP":"49111937247","KOTA":"KAB. PEMALANG","KECAMATAN":"BODEH","DESA":"KEBANDUNGAN","NAMA":"HARJATMO","NAMA_PENERIMA":"HARJATMO","NIK":"3327051008630001","NIK_PENERIMA":"3327051008630001","PEKERJAAN":"","FOTO_URL":"2PBP_49111937247.jpg","STATUS":"AWAL","RT":3,"RW":1,"TANGGAL":""},{"NO":"35","NO_PBP":"49111937249","KOTA":"KAB. PEMALANG","KECAMATAN":"BODEH","DESA":"KEBANDUNGAN","NAMA":"HERI SUSWANTI","NAMA_PENERIMA":"HERI SUSWANTI","NIK":"3327055405820006","NIK_PENERIMA":"3327055405820006","PEKERJAAN":"","FOTO_URL":"2PBP_49111937249.jpg","STATUS":"AWAL","RT":3,"RW":2,"TANGGAL":""},{"NO":"36","NO_PBP":"49111937250","KOTA":"KAB. PEMALANG","KECAMATAN":"BODEH","DESA":"KEBANDUNGAN","NAMA":"JARINTO","NAMA_PENERIMA":"KHOTIMATUL KHASNAAH","NIK":"3327050912830004","NIK_PENERIMA":"3327055806900001","PEKERJAAN":"","FOTO_URL":"2PBP_49111937250.jpg","STATUS":"AWAL","RT":3,"RW":4,"TANGGAL":""},{"NO":"37","NO_PBP":"49111937251","KOTA":"KAB. PEMALANG","KECAMATAN":"BODEH","DESA":"KEBANDUNGAN","NAMA":"JOKO UTOMO","NAMA_PENERIMA":"JOKO UTOMO","NIK":"3327052102830005","NIK_PENERIMA":"3327052102830005","PEKERJAAN":"","FOTO_URL":"2PBP_49111937251.jpg","STATUS":"AWAL","RT":2,"RW":2,"TANGGAL":""},{"NO":"38","NO_PBP":"49111937337","KOTA":"KAB. PEMALANG","KECAMATAN":"BODEH","DESA":"KEBANDUNGAN","NAMA":"JUBAEDAH","NAMA_PENERIMA":"JUBAEDAH","NIK":"3327054601650002","NIK_PENERIMA":"3327054601650002","PEKERJAAN":"","FOTO_URL":"2PBP_49111937337.jpg","STATUS":"AWAL","RT":0,"RW":0,"TANGGAL":""},{"NO":"39","NO_PBP":"49111937379","KOTA":"KAB. PEMALANG","KECAMATAN":"BODEH","DESA":"KEBANDUNGAN","NAMA":"JULIANTI","NAMA_PENERIMA":"JULIANTI","NIK":"3327057007850003","NIK_PENERIMA":"3327057007850003","PEKERJAAN":"","FOTO_URL":"2PBP_49111937379.jpg","STATUS":"AWAL","RT":0,"RW":0,"TANGGAL":""},{"NO":"40","NO_PBP":"49111937215","KOTA":"KAB. PEMALANG","KECAMATAN":"BODEH","DESA":"KEBANDUNGAN","NAMA":"JUMINAH","NAMA_PENERIMA":"JUMINAH","NIK":"3327054809640002","NIK_PENERIMA":"3327054809640002","PEKERJAAN":"","FOTO_URL":"2PBP_49111937215.jpg","STATUS":"AWAL","RT":0,"RW":0,"TANGGAL":""},{"NO":"41","NO_PBP":"49111937275","KOTA":"KAB. PEMALANG","KECAMATAN":"BODEH","DESA":"KEBANDUNGAN","NAMA":"KANAAH","NAMA_PENERIMA":"KANAAH","NIK":"3327054107510132","NIK_PENERIMA":"3327054107510132","PEKERJAAN":"","FOTO_URL":"2PBP_49111937275.jpg","STATUS":"AWAL","RT":0,"RW":0,"TANGGAL":""},{"NO":"42","NO_PBP":"49111937252","KOTA":"KAB. PEMALANG","KECAMATAN":"BODEH","DESA":"KEBANDUNGAN","NAMA":"KASMONO","NAMA_PENERIMA":"KASMONO","NIK":"3327050506680006","NIK_PENERIMA":"3327050506680006","PEKERJAAN":"","FOTO_URL":"2PBP_49111937252.jpg","STATUS":"AWAL","RT":1,"RW":3,"TANGGAL":""},{"NO":"43","NO_PBP":"49111937253","KOTA":"KAB. PEMALANG","KECAMATAN":"BODEH","DESA":"KEBANDUNGAN","NAMA":"KASMURI","NAMA_PENERIMA":"DAUNI","NIK":"3327052104560002","NIK_PENERIMA":"3327055108610001","PEKERJAAN":"","FOTO_URL":"2PBP_49111937253.jpg","STATUS":"AWAL","RT":3,"RW":3,"TANGGAL":""},{"NO":"44","NO_PBP":"49111937373","KOTA":"KAB. PEMALANG","KECAMATAN":"BODEH","DESA":"KEBANDUNGAN","NAMA":"KASTOYO","NAMA_PENERIMA":"KASTOYO","NIK":"3327050107620218","NIK_PENERIMA":"3327050107620218","PEKERJAAN":"","FOTO_URL":"2PBP_49111937373.jpg","STATUS":"AWAL","RT":0,"RW":0,"TANGGAL":""},{"NO":"45","NO_PBP":"49111937254","KOTA":"KAB. PEMALANG","KECAMATAN":"BODEH","DESA":"KEBANDUNGAN","NAMA":"KASTURI","NAMA_PENERIMA":"KASANAH","NIK":"3327050107460021","NIK_PENERIMA":"3327054611690004","PEKERJAAN":"","FOTO_URL":"2PBP_49111937254.jpg","STATUS":"PERWAKILAN","RT_PENERIMA":"003","RW_PENERIMA":"002","ALASAN":"Sakit","RT":3,"RW":2,"TANGGAL":""},{"NO":"46","NO_PBP":"49111937255","KOTA":"KAB. PEMALANG","KECAMATAN":"BODEH","DESA":"KEBANDUNGAN","NAMA":"KHAYATUN NUFUS","NAMA_PENERIMA":"KHAYATUN NUFUS","NIK":"3327052506690002","NIK_PENERIMA":"3327052506690002","PEKERJAAN":"","FOTO_URL":"2PBP_49111937255.jpg","STATUS":"AWAL","RT":2,"RW":1,"TANGGAL":""},{"NO":"47","NO_PBP":"49111937256","KOTA":"KAB. PEMALANG","KECAMATAN":"BODEH","DESA":"KEBANDUNGAN","NAMA":"KHIKMAH","NAMA_PENERIMA":"KHIKMAH","NIK":"3327051807750004","NIK_PENERIMA":"3327051807750004","PEKERJAAN":"","FOTO_URL":"2PBP_49111937256.jpg","STATUS":"AWAL","RT":2,"RW":2,"TANGGAL":""},{"NO":"48","NO_PBP":"49111937212","KOTA":"KAB. PEMALANG","KECAMATAN":"BODEH","DESA":"KEBANDUNGAN","NAMA":"KHUMAEROH","NAMA_PENERIMA":"RAHONO","NIK":"3327055904690003","NIK_PENERIMA":"3327081107550001","PEKERJAAN":"","FOTO_URL":"2PBP_49111937212.jpg","STATUS":"AWAL","RT":0,"RW":0,"TANGGAL":""},{"NO":"49","NO_PBP":"49111937347","KOTA":"KAB. PEMALANG","KECAMATAN":"BODEH","DESA":"KEBANDUNGAN","NAMA":"KUNAEROH","NAMA_PENERIMA":"KUNAEROH","NIK":"3327054704620003","NIK_PENERIMA":"3327054704620003","PEKERJAAN":"","FOTO_URL":"2PBP_49111937347.jpg","STATUS":"AWAL","RT":0,"RW":0,"TANGGAL":""},{"NO":"50","NO_PBP":"49111937257","KOTA":"KAB. PEMALANG","KECAMATAN":"BODEH","DESA":"KEBANDUNGAN","NAMA":"KUNDARI","NAMA_PENERIMA":"KUNDARI","NIK":"3357051707540002","NIK_PENERIMA":"3357051707540002","PEKERJAAN":"","FOTO_URL":"2PBP_49111937257.jpg","STATUS":"AWAL","RT":2,"RW":1,"TANGGAL":""},{"NO":"51","NO_PBP":"49111937370","KOTA":"KAB. PEMALANG","KECAMATAN":"BODEH","DESA":"KEBANDUNGAN","NAMA":"KUNDIYAH","NAMA_PENERIMA":"ARISTO AORIKHI","NIK":"3327054605710002","NIK_PENERIMA":"3327052603630002","PEKERJAAN":"","FOTO_URL":"2PBP_49111937370.jpg","STATUS":"AWAL","RT":0,"RW":0,"TANGGAL":""},{"NO":"52","NO_PBP":"49111937258","KOTA":"KAB. PEMALANG","KECAMATAN":"BODEH","DESA":"KEBANDUNGAN","NAMA":"KUSMIYATUN","NAMA_PENERIMA":"KUSMIYATUN","NIK":"3327056104680001","NIK_PENERIMA":"3327056104680001","PEKERJAAN":"","FOTO_URL":"2PBP_49111937258.jpg","STATUS":"AWAL","RT":2,"RW":3,"TANGGAL":""},{"NO":"53","NO_PBP":"49111937259","KOTA":"KAB. PEMALANG","KECAMATAN":"BODEH","DESA":"KEBANDUNGAN","NAMA":"KUSWANTO","NAMA_PENERIMA":"KUSWANTO","NIK":"3326091008860003","NIK_PENERIMA":"3326091008860003","PEKERJAAN":"","FOTO_URL":"2PBP_49111937259.jpg","STATUS":"AWAL","RT":2,"RW":3,"TANGGAL":""},{"NO":"54","NO_PBP":"49111937260","KOTA":"KAB. PEMALANG","KECAMATAN":"BODEH","DESA":"KEBANDUNGAN","NAMA":"KUSWIYANTO","NAMA_PENERIMA":"MUNAROH","NIK":"3327050802810004","NIK_PENERIMA":"3327055501830003","PEKERJAAN":"","FOTO_URL":"2PBP_49111937260.jpg","STATUS":"AWAL","RT":1,"RW":2,"TANGGAL":""},{"NO":"55","NO_PBP":"49111937261","KOTA":"KAB. PEMALANG","KECAMATAN":"BODEH","DESA":"KEBANDUNGAN","NAMA":"KUSWOYO","NAMA_PENERIMA":"MUNAWIROH","NIK":"3327050211850005","NIK_PENERIMA":"3327055411830005","PEKERJAAN":"","FOTO_URL":"2PBP_49111937261.jpg","STATUS":"AWAL","RT":1,"RW":1,"TANGGAL":""},{"NO":"56","NO_PBP":"49111937262","KOTA":"KAB. PEMALANG","KECAMATAN":"BODEH","DESA":"KEBANDUNGAN","NAMA":"LINA SETIAWATI","NAMA_PENERIMA":"LINA SETIAWATI","NIK":"3327055807850009","NIK_PENERIMA":"3327055807850009","PEKERJAAN":"","FOTO_URL":"2PBP_49111937262.jpg","STATUS":"AWAL","RT":1,"RW":2,"TANGGAL":""},{"NO":"57","NO_PBP":"49111937279","KOTA":"KAB. PEMALANG","KECAMATAN":"BODEH","DESA":"KEBANDUNGAN","NAMA":"LISTIANINGSIH","NAMA_PENERIMA":"LISTIANINGSIH","NIK":"3327056910890003","NIK_PENERIMA":"3327056910890003","PEKERJAAN":"","FOTO_URL":"2PBP_49111937279.jpg","STATUS":"AWAL","RT":0,"RW":0,"TANGGAL":""},{"NO":"58","NO_PBP":"49111937264","KOTA":"KAB. PEMALANG","KECAMATAN":"BODEH","DESA":"KEBANDUNGAN","NAMA":"M. SAPII","NAMA_PENERIMA":"SUMAENI","NIK":"3327051208800008","NIK_PENERIMA":"3327054305800002","PEKERJAAN":"","FOTO_URL":"2PBP_49111937264.jpg","STATUS":"AWAL","RT":2,"RW":4,"TANGGAL":""},{"NO":"59","NO_PBP":"49111937265","KOTA":"KAB. PEMALANG","KECAMATAN":"BODEH","DESA":"KEBANDUNGAN","NAMA":"MAHMURODI","NAMA_PENERIMA":"BEJA TIMAH","NIK":"3327054102762062","NIK_PENERIMA":"3327055103620001","PEKERJAAN":"","FOTO_URL":"2PBP_49111937265.jpg","STATUS":"AWAL","RT":4,"RW":3,"TANGGAL":""},{"NO":"60","NO_PBP":"49111937266","KOTA":"KAB. PEMALANG","KECAMATAN":"BODEH","DESA":"KEBANDUNGAN","NAMA":"MAIYAH","NAMA_PENERIMA":"MAIYAH","NIK":"3327056007590002","NIK_PENERIMA":"3327056007590002","PEKERJAAN":"","FOTO_URL":"2PBP_49111937266.jpg","STATUS":"AWAL","RT":0,"RW":0,"TANGGAL":""},{"NO":"61","NO_PBP":"49111937319","KOTA":"KAB. PEMALANG","KECAMATAN":"BODEH","DESA":"KEBANDUNGAN","NAMA":"MALIKHATUN ANDIYAH","NAMA_PENERIMA":"MALIKHATUN ANDIYAH","NIK":"3327056701940007","NIK_PENERIMA":"3327056701940007","PEKERJAAN":"","FOTO_URL":"2PBP_49111937319.jpg","STATUS":"AWAL","RT":0,"RW":0,"TANGGAL":""},{"NO":"62","NO_PBP":"49111937380","KOTA":"KAB. PEMALANG","KECAMATAN":"BODEH","DESA":"KEBANDUNGAN","NAMA":"MASANAH","NAMA_PENERIMA":"MASANAH","NIK":"3327054512670006","NIK_PENERIMA":"3327054512670006","PEKERJAAN":"","FOTO_URL":"2PBP_49111937380.jpg","STATUS":"AWAL","RT":0,"RW":0,"TANGGAL":""},{"NO":"63","NO_PBP":"49111937378","KOTA":"KAB. PEMALANG","KECAMATAN":"BODEH","DESA":"KEBANDUNGAN","NAMA":"MEISIN SITI KHOTIJAH","NAMA_PENERIMA":"MEISIN SITI KHOTIJAH","NIK":"3327056005900007","NIK_PENERIMA":"3327056005900007","PEKERJAAN":"","FOTO_URL":"2PBP_49111937378.jpg","STATUS":"AWAL","RT":0,"RW":0,"TANGGAL":""},{"NO":"64","NO_PBP":"49111937271","KOTA":"KAB. PEMALANG","KECAMATAN":"BODEH","DESA":"KEBANDUNGAN","NAMA":"MOCHAMAD TISNOYO","NAMA_PENERIMA":"FATMAH WATI","NIK":"3327052208580002","NIK_PENERIMA":"3327055406970002","PEKERJAAN":"","FOTO_URL":"2PBP_49111937271.jpg","STATUS":"PERWAKILAN","RT_PENERIMA":"004","RW_PENERIMA":"003","ALASAN":"Sakit","RT":4,"RW":3,"TANGGAL":""},{"NO":"65","NO_PBP":"49111937272","KOTA":"KAB. PEMALANG","KECAMATAN":"BODEH","DESA":"KEBANDUNGAN","NAMA":"MOH. SUGANTI","NAMA_PENERIMA":"NUR KHOLIDAH","NIK":"3326090703960004","NIK_PENERIMA":"3327056612970002","PEKERJAAN":"","FOTO_URL":"2PBP_49111937272.jpg","STATUS":"AWAL","RT":1,"RW":2,"TANGGAL":""},{"NO":"66","NO_PBP":"49111937273","KOTA":"KAB. PEMALANG","KECAMATAN":"BODEH","DESA":"KEBANDUNGAN","NAMA":"MOH. TAROHIMIN","NAMA_PENERIMA":"RATNASARI","NIK":"3327050308910001","NIK_PENERIMA":"3327055303960002","PEKERJAAN":"","FOTO_URL":"2PBP_49111937273.jpg","STATUS":"AWAL","RT":1,"RW":4,"TANGGAL":""},{"NO":"67","NO_PBP":"49111937293","KOTA":"KAB. PEMALANG","KECAMATAN":"BODEH","DESA":"KEBANDUNGAN","NAMA":"MUAYANAH","NAMA_PENERIMA":"MUAYANAH","NIK":"3327055507800007","NIK_PENERIMA":"3327055507800007","PEKERJAAN":"","FOTO_URL":"2PBP_49111937293.jpg","STATUS":"AWAL","RT":0,"RW":0,"TANGGAL":""},{"NO":"68","NO_PBP":"49111937276","KOTA":"KAB. PEMALANG","KECAMATAN":"BODEH","DESA":"KEBANDUNGAN","NAMA":"MUCHLIDUN","NAMA_PENERIMA":"SITI LAZIMAH","NIK":"3327051404680005","NIK_PENERIMA":"3327056603770001","PEKERJAAN":"","FOTO_URL":"2PBP_49111937276.jpg","STATUS":"AWAL","RT":1,"RW":2,"TANGGAL":""},{"NO":"69","NO_PBP":"49111937277","KOTA":"KAB. PEMALANG","KECAMATAN":"BODEH","DESA":"KEBANDUNGAN","NAMA":"MUHAIMIN","NAMA_PENERIMA":"MISRIYAH","NIK":"3327050512810004","NIK_PENERIMA":"3327054903840009","PEKERJAAN":"","FOTO_URL":"2PBP_49111937277.jpg","STATUS":"AWAL","RT":2,"RW":1,"TANGGAL":""},{"NO":"70","NO_PBP":"49111937278","KOTA":"KAB. PEMALANG","KECAMATAN":"BODEH","DESA":"KEBANDUNGAN","NAMA":"MUHAMAD BASUKI","NAMA_PENERIMA":"MUHAMAD BASUKI","NIK":"3327050107700102","NIK_PENERIMA":"3327050107700102","PEKERJAAN":"","FOTO_URL":"2PBP_49111937278.jpg","STATUS":"AWAL","RT":3,"RW":2,"TANGGAL":""},{"NO":"71","NO_PBP":"49111937280","KOTA":"KAB. PEMALANG","KECAMATAN":"BODEH","DESA":"KEBANDUNGAN","NAMA":"MUHAMAD RUKIMAN","NAMA_PENERIMA":"ATAMAH","NIK":"3327052006810003","NIK_PENERIMA":"3327055808840006","PEKERJAAN":"","FOTO_URL":"2PBP_49111937280.jpg","STATUS":"AWAL","RT":3,"RW":2,"TANGGAL":""},{"NO":"72","NO_PBP":"49111937281","KOTA":"KAB. PEMALANG","KECAMATAN":"BODEH","DESA":"KEBANDUNGAN","NAMA":"MUHAMAD TAOFIK","NAMA_PENERIMA":"MUKAROMAH","NIK":"3327051705860004","NIK_PENERIMA":"3327056905890005","PEKERJAAN":"","FOTO_URL":"2PBP_49111937281.jpg","STATUS":"AWAL","RT":2,"RW":4,"TANGGAL":""},{"NO":"73","NO_PBP":"49111937282","KOTA":"KAB. PEMALANG","KECAMATAN":"BODEH","DESA":"KEBANDUNGAN","NAMA":"MUHAMMAD AFRI NUR ISMAWAN","NAMA_PENERIMA":"DWI PUJI LESTARI","NIK":"3327052203970002","NIK_PENERIMA":"3327056802980001","PEKERJAAN":"","FOTO_URL":"2PBP_49111937282.jpg","STATUS":"AWAL","RT":2,"RW":2,"TANGGAL":""},{"NO":"74","NO_PBP":"49111937283","KOTA":"KAB. PEMALANG","KECAMATAN":"BODEH","DESA":"KEBANDUNGAN","NAMA":"MUHLISIN","NAMA_PENERIMA":"YULAEKHAH","NIK":"3327052105830001","NIK_PENERIMA":"3327055408870002","PEKERJAAN":"","FOTO_URL":"2PBP_49111937283.jpg","STATUS":"AWAL","RT":1,"RW":2,"TANGGAL":""},{"NO":"75","NO_PBP":"49111937284","KOTA":"KAB. PEMALANG","KECAMATAN":"BODEH","DESA":"KEBANDUNGAN","NAMA":"MUKROMIN","NAMA_PENERIMA":"MUKROMIN","NIK":"3327050604060002","NIK_PENERIMA":"3327050604060002","PEKERJAAN":"","FOTO_URL":"2PBP_49111937284.jpg","STATUS":"AWAL","RT":1,"RW":2,"TANGGAL":""},{"NO":"76","NO_PBP":"49111937286","KOTA":"KAB. PEMALANG","KECAMATAN":"BODEH","DESA":"KEBANDUNGAN","NAMA":"MULIKOH","NAMA_PENERIMA":"MULIKOH","NIK":"3302166601900004","NIK_PENERIMA":"3302166601900004","PEKERJAAN":"","FOTO_URL":"2PBP_49111937286.jpg","STATUS":"AWAL","RT":0,"RW":0,"TANGGAL":""},{"NO":"77","NO_PBP":"49111937270","KOTA":"KAB. PEMALANG","KECAMATAN":"BODEH","DESA":"KEBANDUNGAN","NAMA":"MUSLIHAH","NAMA_PENERIMA":"MUSLIHAH","NIK":"3327054201510001","NIK_PENERIMA":"3327054201510001","PEKERJAAN":"","FOTO_URL":"2PBP_49111937270.jpg","STATUS":"AWAL","RT":0,"RW":0,"TANGGAL":""},{"NO":"78","NO_PBP":"49111937289","KOTA":"KAB. PEMALANG","KECAMATAN":"BODEH","DESA":"KEBANDUNGAN","NAMA":"MUSLIKHIN","NAMA_PENERIMA":"SUGIARTI","NIK":"3327050302840001","NIK_PENERIMA":"1803086811900001","PEKERJAAN":"","FOTO_URL":"2PBP_49111937289.jpg","STATUS":"AWAL","RT":1,"RW":2,"TANGGAL":""},{"NO":"79","NO_PBP":"49111937290","KOTA":"KAB. PEMALANG","KECAMATAN":"BODEH","DESA":"KEBANDUNGAN","NAMA":"MUSLIMIN","NAMA_PENERIMA":"TURSIYAH","NIK":"3326091604840002","NIK_PENERIMA":"3327055505890004","PEKERJAAN":"","FOTO_URL":"2PBP_49111937290.jpg","STATUS":"AWAL","RT":1,"RW":2,"TANGGAL":""},{"NO":"80","NO_PBP":"49111937312","KOTA":"KAB. PEMALANG","KECAMATAN":"BODEH","DESA":"KEBANDUNGAN","NAMA":"MUZAYANAH","NAMA_PENERIMA":"MUZAYANAH","NIK":"3328144101880004","NIK_PENERIMA":"3328144101880004","PEKERJAAN":"","FOTO_URL":"2PBP_49111937312.jpg","STATUS":"AWAL","RT":0,"RW":0,"TANGGAL":""},{"NO":"81","NO_PBP":"49111937294","KOTA":"KAB. PEMALANG","KECAMATAN":"BODEH","DESA":"KEBANDUNGAN","NAMA":"NASORI","NAMA_PENERIMA":"SITI TOHIROH","NIK":"3327052601730003","NIK_PENERIMA":"3327054303820011","PEKERJAAN":"","FOTO_URL":"2PBP_49111937294.jpg","STATUS":"AWAL","RT":1,"RW":1,"TANGGAL":""},{"NO":"82","NO_PBP":"49111937288","KOTA":"KAB. PEMALANG","KECAMATAN":"BODEH","DESA":"KEBANDUNGAN","NAMA":"NOVI FITALIA","NAMA_PENERIMA":"NOVI FITALIA","NIK":"3327055311090002","NIK_PENERIMA":"3327055311090002","PEKERJAAN":"","FOTO_URL":"2PBP_49111937288.jpg","STATUS":"AWAL","RT":0,"RW":0,"TANGGAL":""},{"NO":"83","NO_PBP":"49111937296","KOTA":"KAB. PEMALANG","KECAMATAN":"BODEH","DESA":"KEBANDUNGAN","NAMA":"NUR IRFANDI","NAMA_PENERIMA":"KHOERUN NISA","NIK":"3327083010900021","NIK_PENERIMA":"3327054210960005","PEKERJAAN":"","FOTO_URL":"2PBP_49111937296.jpg","STATUS":"AWAL","RT":3,"RW":2,"TANGGAL":""},{"NO":"84","NO_PBP":"49111937291","KOTA":"KAB. PEMALANG","KECAMATAN":"BODEH","DESA":"KEBANDUNGAN","NAMA":"NUR MAYASARI","NAMA_PENERIMA":"NUR MAYASARI","NIK":"3327056105880005","NIK_PENERIMA":"3327056105880005","PEKERJAAN":"","FOTO_URL":"2PBP_49111937291.jpg","STATUS":"AWAL","RT":0,"RW":0,"TANGGAL":""},{"NO":"85","NO_PBP":"49111937297","KOTA":"KAB. PEMALANG","KECAMATAN":"BODEH","DESA":"KEBANDUNGAN","NAMA":"NUR SAIDIN","NAMA_PENERIMA":"SRI PUJIHARSIH","NIK":"3327051509880003","NIK_PENERIMA":"3327084203960061","PEKERJAAN":"","FOTO_URL":"2PBP_49111937297.jpg","STATUS":"AWAL","RT":2,"RW":2,"TANGGAL":""},{"NO":"86","NO_PBP":"49111937298","KOTA":"KAB. PEMALANG","KECAMATAN":"BODEH","DESA":"KEBANDUNGAN","NAMA":"NURIDIN","NAMA_PENERIMA":"KHUSAEROH","NIK":"3327052506890007","NIK_PENERIMA":"3327056203610003","PEKERJAAN":"","FOTO_URL":"2PBP_49111937298.jpg","STATUS":"PERWAKILAN","RT_PENERIMA":"001","RW_PENERIMA":"001","ALASAN":"Bekerja","RT":1,"RW":1,"TANGGAL":""},{"NO":"87","NO_PBP":"49111937299","KOTA":"KAB. PEMALANG","KECAMATAN":"BODEH","DESA":"KEBANDUNGAN","NAMA":"NURKHOLIS","NAMA_PENERIMA":"ISWATUN KHASANAH","NIK":"3327052812840004","NIK_PENERIMA":"3327055409940001","PEKERJAAN":"","FOTO_URL":"2PBP_49111937299.jpg","STATUS":"AWAL","RT":3,"RW":2,"TANGGAL":""},{"NO":"88","NO_PBP":"49111937300","KOTA":"KAB. PEMALANG","KECAMATAN":"BODEH","DESA":"KEBANDUNGAN","NAMA":"NURMAH","NAMA_PENERIMA":"NURMAH","NIK":"3327056905760002","NIK_PENERIMA":"3327056905760002","PEKERJAAN":"","FOTO_URL":"2PBP_49111937300.jpg","STATUS":"AWAL","RT":4,"RW":1,"TANGGAL":""},{"NO":"89","NO_PBP":"49111937302","KOTA":"KAB. PEMALANG","KECAMATAN":"BODEH","DESA":"KEBANDUNGAN","NAMA":"PRATIWI","NAMA_PENERIMA":"PRATIWI","NIK":"3327050107880044","NIK_PENERIMA":"3327050107880044","PEKERJAAN":"","FOTO_URL":"2PBP_49111937302.jpg","STATUS":"AWAL","RT":3,"RW":2,"TANGGAL":""},{"NO":"90","NO_PBP":"49111937305","KOTA":"KAB. PEMALANG","KECAMATAN":"BODEH","DESA":"KEBANDUNGAN","NAMA":"RINANTO","NAMA_PENERIMA":"WASFIYAH","NIK":"3327051402890004","NIK_PENERIMA":"3327056503890004","PEKERJAAN":"","FOTO_URL":"2PBP_49111937305.jpg","STATUS":"AWAL","RT":1,"RW":2,"TANGGAL":""},{"NO":"91","NO_PBP":"49111937306","KOTA":"KAB. PEMALANG","KECAMATAN":"BODEH","DESA":"KEBANDUNGAN","NAMA":"RINTOWO AL MAFTUKHIN","NAMA_PENERIMA":"RINTOWO AL MAFTUKHIN","NIK":"3327052406800001","NIK_PENERIMA":"3327052406800001","PEKERJAAN":"","FOTO_URL":"2PBP_49111937306.jpg","STATUS":"AWAL","RT":3,"RW":2,"TANGGAL":""},{"NO":"92","NO_PBP":"49111937307","KOTA":"KAB. PEMALANG","KECAMATAN":"BODEH","DESA":"KEBANDUNGAN","NAMA":"RISMANTO","NAMA_PENERIMA":"ZUMROTUL KHASANAH","NIK":"3327055709430001","NIK_PENERIMA":"3327054206950001","PEKERJAAN":"","FOTO_URL":"2PBP_49111937307.jpg","STATUS":"PERWAKILAN","RT_PENERIMA":"003","RW_PENERIMA":"002","ALASAN":"Bekerja","RT":3,"RW":2,"TANGGAL":""},{"NO":"93","NO_PBP":"49111937308","KOTA":"KAB. PEMALANG","KECAMATAN":"BODEH","DESA":"KEBANDUNGAN","NAMA":"RIYANTO","NAMA_PENERIMA":"ELISAH","NIK":"3327050602900007","NIK_PENERIMA":"3327055304950004","PEKERJAAN":"","FOTO_URL":"2PBP_49111937308.jpg","STATUS":"AWAL","RT":2,"RW":3,"TANGGAL":""},{"NO":"94","NO_PBP":"49111937241","KOTA":"KAB. PEMALANG","KECAMATAN":"BODEH","DESA":"KEBANDUNGAN","NAMA":"RIZA UMAMI","NAMA_PENERIMA":"ARIF GUNAWAN","NIK":"3327055203000003","NIK_PENERIMA":"3327052511920003","PEKERJAAN":"","FOTO_URL":"2PBP_49111937241.jpg","STATUS":"AWAL","RT":0,"RW":0,"TANGGAL":""},{"NO":"95","NO_PBP":"49111937309","KOTA":"KAB. PEMALANG","KECAMATAN":"BODEH","DESA":"KEBANDUNGAN","NAMA":"ROATUN","NAMA_PENERIMA":"ROATUN","NIK":"3327052010540002","NIK_PENERIMA":"3327052010540002","PEKERJAAN":"","FOTO_URL":"2PBP_49111937309.jpg","STATUS":"AWAL","RT":3,"RW":2,"TANGGAL":""},{"NO":"96","NO_PBP":"49111937310","KOTA":"KAB. PEMALANG","KECAMATAN":"BODEH","DESA":"KEBANDUNGAN","NAMA":"ROHMAN","NAMA_PENERIMA":"ROHMAN","NIK":"3327051505720006","NIK_PENERIMA":"3327051505720006","PEKERJAAN":"","FOTO_URL":"2PBP_49111937310.jpg","STATUS":"AWAL","RT":3,"RW":2,"TANGGAL":""},{"NO":"97","NO_PBP":"49111937311","KOTA":"KAB. PEMALANG","KECAMATAN":"BODEH","DESA":"KEBANDUNGAN","NAMA":"ROMZANAH","NAMA_PENERIMA":"JURIYAH","NIK":"3327055411163003","NIK_PENERIMA":"3327084111630003","PEKERJAAN":"","FOTO_URL":"2PBP_49111937311.jpg","STATUS":"AWAL","RT":1,"RW":1,"TANGGAL":""},{"NO":"98","NO_PBP":"49111937318","KOTA":"KAB. PEMALANG","KECAMATAN":"BODEH","DESA":"KEBANDUNGAN","NAMA":"RONDIYAH","NAMA_PENERIMA":"RONDIYAH","NIK":"3327055910700001","NIK_PENERIMA":"3327055910700001","PEKERJAAN":"","FOTO_URL":"2PBP_49111937318.jpg","STATUS":"AWAL","RT":0,"RW":0,"TANGGAL":""},{"NO":"99","NO_PBP":"49111937313","KOTA":"KAB. PEMALANG","KECAMATAN":"BODEH","DESA":"KEBANDUNGAN","NAMA":"RUKAYAH","NAMA_PENERIMA":"RUKAYAH","NIK":"3327054107580081","NIK_PENERIMA":"3327054107580081","PEKERJAAN":"","FOTO_URL":"2PBP_49111937313.jpg","STATUS":"AWAL","RT":1,"RW":2,"TANGGAL":""},{"NO":"100","NO_PBP":"49111937315","KOTA":"KAB. PEMALANG","KECAMATAN":"BODEH","DESA":"KEBANDUNGAN","NAMA":"RUYATI","NAMA_PENERIMA":"RUYATI","NIK":"3327053112510035","NIK_PENERIMA":"3327053112510035","PEKERJAAN":"","FOTO_URL":"2PBP_49111937315.jpg","STATUS":"AWAL","RT":1,"RW":2,"TANGGAL":""},{"NO":"101","NO_PBP":"49111937317","KOTA":"KAB. PEMALANG","KECAMATAN":"BODEH","DESA":"KEBANDUNGAN","NAMA":"SAEFUL FATONI","NAMA_PENERIMA":"INDAH RIYANTO","NIK":"3327051309790001","NIK_PENERIMA":"3327056008840002","PEKERJAAN":"","FOTO_URL":"2PBP_49111937317.jpg","STATUS":"AWAL","RT":1,"RW":2,"TANGGAL":""},{"NO":"102","NO_PBP":"49111937320","KOTA":"KAB. PEMALANG","KECAMATAN":"BODEH","DESA":"KEBANDUNGAN","NAMA":"SANDRA APRIYANTO","NAMA_PENERIMA":"RINA AGUS SULISTIYONINGSIH","NIK":"3327051804880001","NIK_PENERIMA":"3327084808880011","PEKERJAAN":"","FOTO_URL":"2PBP_49111937320.jpg","STATUS":"AWAL","RT":1,"RW":1,"TANGGAL":""},{"NO":"103","NO_PBP":"49111937321","KOTA":"KAB. PEMALANG","KECAMATAN":"BODEH","DESA":"KEBANDUNGAN","NAMA":"SARIYAH","NAMA_PENERIMA":"UCI LISDINIAWI","NIK":"3327054107380005","NIK_PENERIMA":"3327054705960006","PEKERJAAN":"","FOTO_URL":"2PBP_49111937321.jpg","STATUS":"PERWAKILAN","RT_PENERIMA":"001","RW_PENERIMA":"003","ALASAN":"Manula","RT":0,"RW":0,"TANGGAL":""},{"NO":"104","NO_PBP":"49111937322","KOTA":"KAB. PEMALANG","KECAMATAN":"BODEH","DESA":"KEBANDUNGAN","NAMA":"SARIYATUN","NAMA_PENERIMA":"SARIYATUN","NIK":"3327055005690002","NIK_PENERIMA":"3327055005690002","PEKERJAAN":"","FOTO_URL":"2PBP_49111937322.jpg","STATUS":"AWAL","RT":2,"RW":1,"TANGGAL":""},{"NO":"105","NO_PBP":"49111937360","KOTA":"KAB. PEMALANG","KECAMATAN":"BODEH","DESA":"KEBANDUNGAN","NAMA":"SATISAH","NAMA_PENERIMA":"SATISAH","NIK":"3327055511630001","NIK_PENERIMA":"3327055511630001","PEKERJAAN":"","FOTO_URL":"2PBP_49111937360.jpg","STATUS":"AWAL","RT":0,"RW":0,"TANGGAL":""},{"NO":"106","NO_PBP":"49111937324","KOTA":"KAB. PEMALANG","KECAMATAN":"BODEH","DESA":"KEBANDUNGAN","NAMA":"SIGIT PRIONO","NAMA_PENERIMA":"NURSIH","NIK":"3327112709870005","NIK_PENERIMA":"3327056804900009","PEKERJAAN":"","FOTO_URL":"2PBP_49111937324.jpg","STATUS":"AWAL","RT":2,"RW":2,"TANGGAL":""},{"NO":"107","NO_PBP":"49111937325","KOTA":"KAB. PEMALANG","KECAMATAN":"BODEH","DESA":"KEBANDUNGAN","NAMA":"SINAR","NAMA_PENERIMA":"SRI WINARNI","NIK":"3327052211760003","NIK_PENERIMA":"3327055904830004","PEKERJAAN":"","FOTO_URL":"2PBP_49111937325.jpg","STATUS":"AWAL","RT":1,"RW":2,"TANGGAL":""},{"NO":"108","NO_PBP":"49111937326","KOTA":"KAB. PEMALANG","KECAMATAN":"BODEH","DESA":"KEBANDUNGAN","NAMA":"SISWANTO","NAMA_PENERIMA":"KUNASRI","NIK":"3327052506800003","NIK_PENERIMA":"3327054102630010","PEKERJAAN":"","FOTO_URL":"2PBP_49111937326.jpg","STATUS":"PERWAKILAN","RT_PENERIMA":"003","RW_PENERIMA":"002","ALASAN":"Bekerja","RT":3,"RW":2,"TANGGAL":""},{"NO":"109","NO_PBP":"49111937327","KOTA":"KAB. PEMALANG","KECAMATAN":"BODEH","DESA":"KEBANDUNGAN","NAMA":"SISWOYO","NAMA_PENERIMA":"ASROPIYAH","NIK":"3326090904830001","NIK_PENERIMA":"3327055807890002","PEKERJAAN":"","FOTO_URL":"2PBP_49111937327.jpg","STATUS":"AWAL","RT":4,"RW":3,"TANGGAL":""},{"NO":"110","NO_PBP":"49111937329","KOTA":"KAB. PEMALANG","KECAMATAN":"BODEH","DESA":"KEBANDUNGAN","NAMA":"SITI GIYANTI","NAMA_PENERIMA":"SITI GIYANTI","NIK":"3327056709890002","NIK_PENERIMA":"3327056709890002","PEKERJAAN":"","FOTO_URL":"2PBP_49111937329.jpg","STATUS":"AWAL","RT":3,"RW":2,"TANGGAL":""},{"NO":"111","NO_PBP":"49111937330","KOTA":"KAB. PEMALANG","KECAMATAN":"BODEH","DESA":"KEBANDUNGAN","NAMA":"SITI KHUJAEMATUN","NAMA_PENERIMA":"SITI KHUJAEMATUN","NIK":"3327057112660030","NIK_PENERIMA":"3327057112660030","PEKERJAAN":"","FOTO_URL":"2PBP_49111937330.jpg","STATUS":"AWAL","RT":2,"RW":1,"TANGGAL":""},{"NO":"112","NO_PBP":"49111937331","KOTA":"KAB. PEMALANG","KECAMATAN":"BODEH","DESA":"KEBANDUNGAN","NAMA":"SITI MAESAROH","NAMA_PENERIMA":"SITI MAESAROH","NIK":"3327055208510002","NIK_PENERIMA":"3327055208510002","PEKERJAAN":"","FOTO_URL":"2PBP_49111937331.jpg","STATUS":"AWAL","RT":2,"RW":1,"TANGGAL":""},{"NO":"113","NO_PBP":"49111937220","KOTA":"KAB. PEMALANG","KECAMATAN":"BODEH","DESA":"KEBANDUNGAN","NAMA":"SITI MAESAROH","NAMA_PENERIMA":"SITI MAESAROH","NIK":"3327056202680004","NIK_PENERIMA":"3327056202680004","PEKERJAAN":"","FOTO_URL":"2PBP_49111937220.jpg","STATUS":"AWAL","RT":0,"RW":0,"TANGGAL":""},{"NO":"114","NO_PBP":"49111937357","KOTA":"KAB. PEMALANG","KECAMATAN":"BODEH","DESA":"KEBANDUNGAN","NAMA":"SITI MARYAM","NAMA_PENERIMA":"SITI MARYAM","NIK":"3327054608630003","NIK_PENERIMA":"3327054608630003","PEKERJAAN":"","FOTO_URL":"2PBP_49111937357.jpg","STATUS":"AWAL","RT":0,"RW":0,"TANGGAL":""},{"NO":"115","NO_PBP":"49111937332","KOTA":"KAB. PEMALANG","KECAMATAN":"BODEH","DESA":"KEBANDUNGAN","NAMA":"SITI UMROH","NAMA_PENERIMA":"SITI UMROH","NIK":"3327051604850006","NIK_PENERIMA":"3327051604850006","PEKERJAAN":"","FOTO_URL":"2PBP_49111937332.jpg","STATUS":"AWAL","RT":2,"RW":1,"TANGGAL":""},{"NO":"116","NO_PBP":"49111937333","KOTA":"KAB. PEMALANG","KECAMATAN":"BODEH","DESA":"KEBANDUNGAN","NAMA":"SLAMET TINGGAL","NAMA_PENERIMA":"SITI NURIDA","NIK":"3326152012890001","NIK_PENERIMA":"3327054403920002","PEKERJAAN":"","FOTO_URL":"2PBP_49111937333.jpg","STATUS":"AWAL","RT":2,"RW":1,"TANGGAL":""},{"NO":"117","NO_PBP":"49111937292","KOTA":"KAB. PEMALANG","KECAMATAN":"BODEH","DESA":"KEBANDUNGAN","NAMA":"SOBIRIN","NAMA_PENERIMA":"MUFRODAH","NIK":"3327050105550001","NIK_PENERIMA":"3327056704850004","PEKERJAAN":"","FOTO_URL":"2PBP_49111937292.jpg","STATUS":"PERWAKILAN","RT_PENERIMA":"003","RW_PENERIMA":"004","ALASAN":"Sakit","RT":0,"RW":0,"TANGGAL":""},{"NO":"118","NO_PBP":"49111937334","KOTA":"KAB. PEMALANG","KECAMATAN":"BODEH","DESA":"KEBANDUNGAN","NAMA":"SOHIRIN","NAMA_PENERIMA":"SOHIRIN","NIK":"3327050409670002","NIK_PENERIMA":"3327050409670002","PEKERJAAN":"","FOTO_URL":"2PBP_49111937334.jpg","STATUS":"AWAL","RT":2,"RW":2,"TANGGAL":""},{"NO":"119","NO_PBP":"49111937335","KOTA":"KAB. PEMALANG","KECAMATAN":"BODEH","DESA":"KEBANDUNGAN","NAMA":"SOLEKHUDIN","NAMA_PENERIMA":"SOLEKHUDIN","NIK":"3327052307830007","NIK_PENERIMA":"3327052307830007","PEKERJAAN":"","FOTO_URL":"2PBP_49111937335.jpg","STATUS":"AWAL","RT":2,"RW":2,"TANGGAL":""},{"NO":"120","NO_PBP":"49111937336","KOTA":"KAB. PEMALANG","KECAMATAN":"BODEH","DESA":"KEBANDUNGAN","NAMA":"SOPIYAH","NAMA_PENERIMA":"SOPIYAH","NIK":"3327054107660192","NIK_PENERIMA":"3327054107660192","PEKERJAAN":"","FOTO_URL":"2PBP_49111937336.jpg","STATUS":"AWAL","RT":4,"RW":3,"TANGGAL":""},{"NO":"121","NO_PBP":"49111937316","KOTA":"KAB. PEMALANG","KECAMATAN":"BODEH","DESA":"KEBANDUNGAN","NAMA":"SRI UTAMI","NAMA_PENERIMA":"SRI UTAMI","NIK":"3327056008580001","NIK_PENERIMA":"3327056008580001","PEKERJAAN":"","FOTO_URL":"2PBP_49111937316.jpg","STATUS":"AWAL","RT":0,"RW":0,"TANGGAL":""},{"NO":"122","NO_PBP":"49111937356","KOTA":"KAB. PEMALANG","KECAMATAN":"BODEH","DESA":"KEBANDUNGAN","NAMA":"SRI WIDOWATI","NAMA_PENERIMA":"SRI WIDOWATI","NIK":"3327055002640002","NIK_PENERIMA":"3327055002640002","PEKERJAAN":"","FOTO_URL":"2PBP_49111937356.jpg","STATUS":"AWAL","RT":0,"RW":0,"TANGGAL":""},{"NO":"123","NO_PBP":"49111937303","KOTA":"KAB. PEMALANG","KECAMATAN":"BODEH","DESA":"KEBANDUNGAN","NAMA":"SRI WIHESTI","NAMA_PENERIMA":"SRI WIHESTI","NIK":"3327056109650002","NIK_PENERIMA":"3327056109650002","PEKERJAAN":"","FOTO_URL":"2PBP_49111937303.jpg","STATUS":"AWAL","RT":0,"RW":0,"TANGGAL":""},{"NO":"124","NO_PBP":"49111937328","KOTA":"KAB. PEMALANG","KECAMATAN":"BODEH","DESA":"KEBANDUNGAN","NAMA":"SUBADRIYAH","NAMA_PENERIMA":"SUBADRIYAH","NIK":"3327054804640004","NIK_PENERIMA":"3327054804640004","PEKERJAAN":"","FOTO_URL":"2PBP_49111937328.jpg","STATUS":"AWAL","RT":0,"RW":0,"TANGGAL":""},{"NO":"125","NO_PBP":"49111937338","KOTA":"KAB. PEMALANG","KECAMATAN":"BODEH","DESA":"KEBANDUNGAN","NAMA":"SUDARMO","NAMA_PENERIMA":"NUR ASIYAH","NIK":"3327050101820006","NIK_PENERIMA":"3327057112850006","PEKERJAAN":"","FOTO_URL":"2PBP_49111937338.jpg","STATUS":"AWAL","RT":1,"RW":2,"TANGGAL":""},{"NO":"126","NO_PBP":"49111937339","KOTA":"KAB. PEMALANG","KECAMATAN":"BODEH","DESA":"KEBANDUNGAN","NAMA":"SUDARTO","NAMA_PENERIMA":"SUDARTO","NIK":"3327050902550002","NIK_PENERIMA":"3327050902550002","PEKERJAAN":"","FOTO_URL":"2PBP_49111937339.jpg","STATUS":"AWAL","RT":0,"RW":0,"TANGGAL":""},{"NO":"127","NO_PBP":"49111937340","KOTA":"KAB. PEMALANG","KECAMATAN":"BODEH","DESA":"KEBANDUNGAN","NAMA":"SUGIYANTO","NAMA_PENERIMA":"KUNDRIYAH","NIK":"3327050702800005","NIK_PENERIMA":"3327054201830007","PEKERJAAN":"","FOTO_URL":"2PBP_49111937340.jpg","STATUS":"AWAL","RT":2,"RW":4,"TANGGAL":""},{"NO":"128","NO_PBP":"49111937341","KOTA":"KAB. PEMALANG","KECAMATAN":"BODEH","DESA":"KEBANDUNGAN","NAMA":"SUHADI","NAMA_PENERIMA":"SUHADI","NIK":"3327050805520001","NIK_PENERIMA":"3327050805520001","PEKERJAAN":"","FOTO_URL":"2PBP_49111937341.jpg","STATUS":"AWAL","RT":2,"RW":4,"TANGGAL":""},{"NO":"129","NO_PBP":"49111937343","KOTA":"KAB. PEMALANG","KECAMATAN":"BODEH","DESA":"KEBANDUNGAN","NAMA":"SUHERMAN","NAMA_PENERIMA":"FATMAWATI","NIK":"3327054511920004","NIK_PENERIMA":"3327055306700001","PEKERJAAN":"","FOTO_URL":"2PBP_49111937343.jpg","STATUS":"PERWAKILAN","RT_PENERIMA":"003","RW_PENERIMA":"002","ALASAN":"Bekerja","RT":3,"RW":2,"TANGGAL":""},{"NO":"130","NO_PBP":"49111937345","KOTA":"KAB. PEMALANG","KECAMATAN":"BODEH","DESA":"KEBANDUNGAN","NAMA":"SUIDAH","NAMA_PENERIMA":"SUIDAH","NIK":"3327051604920010","NIK_PENERIMA":"3327051604920010","PEKERJAAN":"","FOTO_URL":"2PBP_49111937345.jpg","STATUS":"AWAL","RT":1,"RW":3,"TANGGAL":""},{"NO":"131","NO_PBP":"49111937346","KOTA":"KAB. PEMALANG","KECAMATAN":"BODEH","DESA":"KEBANDUNGAN","NAMA":"SUKARDI","NAMA_PENERIMA":"SRI LISTIYOWATI","NIK":"3327052309820002","NIK_PENERIMA":"3327115705900008","PEKERJAAN":"","FOTO_URL":"2PBP_49111937346.jpg","STATUS":"AWAL","RT":1,"RW":2,"TANGGAL":""},{"NO":"132","NO_PBP":"49111937236","KOTA":"KAB. PEMALANG","KECAMATAN":"BODEH","DESA":"KEBANDUNGAN","NAMA":"SUNARTI","NAMA_PENERIMA":"SUNARTI","NIK":"3327054107550095","NIK_PENERIMA":"3327054107550095","PEKERJAAN":"","FOTO_URL":"2PBP_49111937236.jpg","STATUS":"AWAL","RT":0,"RW":0,"TANGGAL":""},{"NO":"133","NO_PBP":"49111937348","KOTA":"KAB. PEMALANG","KECAMATAN":"BODEH","DESA":"KEBANDUNGAN","NAMA":"SUNARTI","NAMA_PENERIMA":"SUNARTI","NIK":"3327051006720005","NIK_PENERIMA":"3327051006720005","PEKERJAAN":"","FOTO_URL":"2PBP_49111937348.jpg","STATUS":"AWAL","RT":4,"RW":1,"TANGGAL":""},{"NO":"134","NO_PBP":"49111937342","KOTA":"KAB. PEMALANG","KECAMATAN":"BODEH","DESA":"KEBANDUNGAN","NAMA":"SUPARTI","NAMA_PENERIMA":"SUPARTI","NIK":"3327054201690001","NIK_PENERIMA":"3327054201690001","PEKERJAAN":"","FOTO_URL":"2PBP_49111937342.jpg","STATUS":"AWAL","RT":0,"RW":0,"TANGGAL":""},{"NO":"135","NO_PBP":"49111937349","KOTA":"KAB. PEMALANG","KECAMATAN":"BODEH","DESA":"KEBANDUNGAN","NAMA":"SUPRIYANTO","NAMA_PENERIMA":"MUDRISAH","NIK":"3502131803800001","NIK_PENERIMA":"3327055803770003","PEKERJAAN":"","FOTO_URL":"2PBP_49111937349.jpg","STATUS":"AWAL","RT":1,"RW":3,"TANGGAL":""},{"NO":"136","NO_PBP":"49111937268","KOTA":"KAB. PEMALANG","KECAMATAN":"BODEH","DESA":"KEBANDUNGAN","NAMA":"SURATMO","NAMA_PENERIMA":"SURATMO","NIK":"3327051310550002","NIK_PENERIMA":"3327051310550002","PEKERJAAN":"","FOTO_URL":"2PBP_49111937268.jpg","STATUS":"AWAL","RT":0,"RW":0,"TANGGAL":""},{"NO":"137","NO_PBP":"49111937350","KOTA":"KAB. PEMALANG","KECAMATAN":"BODEH","DESA":"KEBANDUNGAN","NAMA":"SURATNO","NAMA_PENERIMA":"MUNDIYAH","NIK":"3327050605620005","NIK_PENERIMA":"3327054206670002","PEKERJAAN":"","FOTO_URL":"2PBP_49111937350.jpg","STATUS":"AWAL","RT":1,"RW":4,"TANGGAL":""},{"NO":"138","NO_PBP":"49111937351","KOTA":"KAB. PEMALANG","KECAMATAN":"BODEH","DESA":"KEBANDUNGAN","NAMA":"SURTINAH","NAMA_PENERIMA":"SURTINAH","NIK":"3327054107630477","NIK_PENERIMA":"3327054107630477","PEKERJAAN":"","FOTO_URL":"2PBP_49111937351.jpg","STATUS":"AWAL","RT":1,"RW":3,"TANGGAL":""},{"NO":"139","NO_PBP":"49111937263","KOTA":"KAB. PEMALANG","KECAMATAN":"BODEH","DESA":"KEBANDUNGAN","NAMA":"SURYANI","NAMA_PENERIMA":"SURYANI","NIK":"3327056401880003","NIK_PENERIMA":"3327056401880003","PEKERJAAN":"","FOTO_URL":"2PBP_49111937263.jpg","STATUS":"AWAL","RT":0,"RW":0,"TANGGAL":""},{"NO":"140","NO_PBP":"49111937352","KOTA":"KAB. PEMALANG","KECAMATAN":"BODEH","DESA":"KEBANDUNGAN","NAMA":"SUSISTO","NAMA_PENERIMA":"SRI MUKTI","NIK":"3327050810700001","NIK_PENERIMA":"3327056002720001","PEKERJAAN":"","FOTO_URL":"2PBP_49111937352.jpg","STATUS":"AWAL","RT":2,"RW":4,"TANGGAL":""},{"NO":"141","NO_PBP":"49111937353","KOTA":"KAB. PEMALANG","KECAMATAN":"BODEH","DESA":"KEBANDUNGAN","NAMA":"SUTARI","NAMA_PENERIMA":"SURATMI","NIK":"3327050407460001","NIK_PENERIMA":"3327054107710096","PEKERJAAN":"","FOTO_URL":"2PBP_49111937353.jpg","STATUS":"AWAL","RT":3,"RW":1,"TANGGAL":""},{"NO":"142","NO_PBP":"49111937354","KOTA":"KAB. PEMALANG","KECAMATAN":"BODEH","DESA":"KEBANDUNGAN","NAMA":"SUTARTO","NAMA_PENERIMA":"KHOTIPAH","NIK":"3326102301730001","NIK_PENERIMA":"3327056203860004","PEKERJAAN":"","FOTO_URL":"2PBP_49111937354.jpg","STATUS":"AWAL","RT":1,"RW":2,"TANGGAL":""},{"NO":"143","NO_PBP":"49111937355","KOTA":"KAB. PEMALANG","KECAMATAN":"BODEH","DESA":"KEBANDUNGAN","NAMA":"SUTARYO","NAMA_PENERIMA":"SUTARYO","NIK":"3327052606530001","NIK_PENERIMA":"3327052606530001","PEKERJAAN":"","FOTO_URL":"2PBP_49111937355.jpg","STATUS":"AWAL","RT":1,"RW":2,"TANGGAL":""},{"NO":"144","NO_PBP":"49111937295","KOTA":"KAB. PEMALANG","KECAMATAN":"BODEH","DESA":"KEBANDUNGAN","NAMA":"SUYOSO","NAMA_PENERIMA":"SUYOSO","NIK":"3327051908650001","NIK_PENERIMA":"3327051908650001","PEKERJAAN":"","FOTO_URL":"2PBP_49111937295.jpg","STATUS":"AWAL","RT":0,"RW":0,"TANGGAL":""},{"NO":"145","NO_PBP":"49111937287","KOTA":"KAB. PEMALANG","KECAMATAN":"BODEH","DESA":"KEBANDUNGAN","NAMA":"SYAFIATUN","NAMA_PENERIMA":"SYAFIATUN","NIK":"3327055005890007","NIK_PENERIMA":"3327055005890007","PEKERJAAN":"","FOTO_URL":"2PBP_49111937287.jpg","STATUS":"AWAL","RT":0,"RW":0,"TANGGAL":""},{"NO":"146","NO_PBP":"49111937314","KOTA":"KAB. PEMALANG","KECAMATAN":"BODEH","DESA":"KEBANDUNGAN","NAMA":"TARINAH","NAMA_PENERIMA":"TARINAH","NIK":"3327054604670002","NIK_PENERIMA":"3327054604670002","PEKERJAAN":"","FOTO_URL":"2PBP_49111937314.jpg","STATUS":"AWAL","RT":0,"RW":0,"TANGGAL":""},{"NO":"147","NO_PBP":"49111937358","KOTA":"KAB. PEMALANG","KECAMATAN":"BODEH","DESA":"KEBANDUNGAN","NAMA":"TARINI","NAMA_PENERIMA":"TARINI","NIK":"3327050908820003","NIK_PENERIMA":"3327050908820003","PEKERJAAN":"","FOTO_URL":"2PBP_49111937358.jpg","STATUS":"AWAL","RT":1,"RW":2,"TANGGAL":""},{"NO":"148","NO_PBP":"49111937359","KOTA":"KAB. PEMALANG","KECAMATAN":"BODEH","DESA":"KEBANDUNGAN","NAMA":"TARMAD","NAMA_PENERIMA":"CASLIYAH","NIK":"3327050107420092","NIK_PENERIMA":"3327054107480210","PEKERJAAN":"","FOTO_URL":"2PBP_49111937359.jpg","STATUS":"AWAL","RT":1,"RW":1,"TANGGAL":""},{"NO":"149","NO_PBP":"49111937361","KOTA":"KAB. PEMALANG","KECAMATAN":"BODEH","DESA":"KEBANDUNGAN","NAMA":"TASRIYAH","NAMA_PENERIMA":"SARINTEN","NIK":"3327054107500038","NIK_PENERIMA":"3327055003650002","PEKERJAAN":"","FOTO_URL":"2PBP_49111937361.jpg","STATUS":"AWAL","RT":2,"RW":3,"TANGGAL":""},{"NO":"150","NO_PBP":"49111937246","KOTA":"KAB. PEMALANG","KECAMATAN":"BODEH","DESA":"KEBANDUNGAN","NAMA":"TOBIIN","NAMA_PENERIMA":"SUNDIROH","NIK":"3327051507630001","NIK_PENERIMA":"3327054107710058","PEKERJAAN":"","FOTO_URL":"2PBP_49111937246.jpg","STATUS":"AWAL","RT":0,"RW":0,"TANGGAL":""},{"NO":"151","NO_PBP":"49111937362","KOTA":"KAB. PEMALANG","KECAMATAN":"BODEH","DESA":"KEBANDUNGAN","NAMA":"TOLANI","NAMA_PENERIMA":"SITI YULIATUN","NIK":"3327052804840007","NIK_PENERIMA":"3326097107880003","PEKERJAAN":"","FOTO_URL":"2PBP_49111937362.jpg","STATUS":"AWAL","RT":1,"RW":1,"TANGGAL":""},{"NO":"152","NO_PBP":"49111937364","KOTA":"KAB. PEMALANG","KECAMATAN":"BODEH","DESA":"KEBANDUNGAN","NAMA":"TRI LESTARI","NAMA_PENERIMA":"TRI LESTARI","NIK":"3327050305930003","NIK_PENERIMA":"3327050305930003","PEKERJAAN":"","FOTO_URL":"2PBP_49111937364.jpg","STATUS":"AWAL","RT":1,"RW":2,"TANGGAL":""},{"NO":"153","NO_PBP":"49111937365","KOTA":"KAB. PEMALANG","KECAMATAN":"BODEH","DESA":"KEBANDUNGAN","NAMA":"TRI PUJIATININGSIH","NAMA_PENERIMA":"TRI PUJIATININGSIH","NIK":"3327052612920001","NIK_PENERIMA":"3327052612920001","PEKERJAAN":"","FOTO_URL":"2PBP_49111937365.jpg","STATUS":"AWAL","RT":3,"RW":2,"TANGGAL":""},{"NO":"154","NO_PBP":"49111937366","KOTA":"KAB. PEMALANG","KECAMATAN":"BODEH","DESA":"KEBANDUNGAN","NAMA":"TURIYAH","NAMA_PENERIMA":"TURIYAH","NIK":"3327055801500001","NIK_PENERIMA":"3327055801500001","PEKERJAAN":"","FOTO_URL":"2PBP_49111937366.jpg","STATUS":"AWAL","RT":1,"RW":2,"TANGGAL":""},{"NO":"155","NO_PBP":"49111937274","KOTA":"KAB. PEMALANG","KECAMATAN":"BODEH","DESA":"KEBANDUNGAN","NAMA":"TURIYAH","NAMA_PENERIMA":"TURIYAH","NIK":"3327055501690004","NIK_PENERIMA":"3327055501690004","PEKERJAAN":"","FOTO_URL":"2PBP_49111937274.jpg","STATUS":"AWAL","RT":0,"RW":0,"TANGGAL":""},{"NO":"156","NO_PBP":"49111937367","KOTA":"KAB. PEMALANG","KECAMATAN":"BODEH","DESA":"KEBANDUNGAN","NAMA":"TURMUDI","NAMA_PENERIMA":"TURMUDI","NIK":"3327050107450100","NIK_PENERIMA":"3327050107450100","PEKERJAAN":"","FOTO_URL":"2PBP_49111937367.jpg","STATUS":"AWAL","RT":3,"RW":4,"TANGGAL":""},{"NO":"157","NO_PBP":"49111937368","KOTA":"KAB. PEMALANG","KECAMATAN":"BODEH","DESA":"KEBANDUNGAN","NAMA":"TUTI TUROHMI","NAMA_PENERIMA":"TUTI TUROHMI","NIK":"3327052703790005","NIK_PENERIMA":"3327052703790005","PEKERJAAN":"","FOTO_URL":"2PBP_49111937368.jpg","STATUS":"AWAL","RT":2,"RW":1,"TANGGAL":""},{"NO":"158","NO_PBP":"49111937369","KOTA":"KAB. PEMALANG","KECAMATAN":"BODEH","DESA":"KEBANDUNGAN","NAMA":"UGIYANTO","NAMA_PENERIMA":"UGIYANTO","NIK":"3327051103780007","NIK_PENERIMA":"3327051103780007","PEKERJAAN":"","FOTO_URL":"2PBP_49111937369.jpg","STATUS":"AWAL","RT":3,"RW":2,"TANGGAL":""},{"NO":"159","NO_PBP":"49111937269","KOTA":"KAB. PEMALANG","KECAMATAN":"BODEH","DESA":"KEBANDUNGAN","NAMA":"UMIYATI","NAMA_PENERIMA":"UMIYATI","NIK":"3327054801970001","NIK_PENERIMA":"3327054801970001","PEKERJAAN":"","FOTO_URL":"2PBP_49111937269.jpg","STATUS":"AWAL","RT":0,"RW":0,"TANGGAL":""},{"NO":"160","NO_PBP":"49111937371","KOTA":"KAB. PEMALANG","KECAMATAN":"BODEH","DESA":"KEBANDUNGAN","NAMA":"UNTUNG","NAMA_PENERIMA":"NUR ISNAENI","NIK":"3327050806910008","NIK_PENERIMA":"3327054102930012","PEKERJAAN":"","FOTO_URL":"2PBP_49111937371.jpg","STATUS":"AWAL","RT":3,"RW":2,"TANGGAL":""},{"NO":"161","NO_PBP":"49111937372","KOTA":"KAB. PEMALANG","KECAMATAN":"BODEH","DESA":"KEBANDUNGAN","NAMA":"WAHYU","NAMA_PENERIMA":"DARTIYAH","NIK":"3202030701870003","NIK_PENERIMA":"3327054610890005","PEKERJAAN":"","FOTO_URL":"2PBP_49111937372.jpg","STATUS":"AWAL","RT":1,"RW":3,"TANGGAL":""},{"NO":"162","NO_PBP":"49111937363","KOTA":"KAB. PEMALANG","KECAMATAN":"BODEH","DESA":"KEBANDUNGAN","NAMA":"WARLI","NAMA_PENERIMA":"WARLI","NIK":"3327050107670058","NIK_PENERIMA":"3327050107670058","PEKERJAAN":"","FOTO_URL":"2PBP_49111937363.jpg","STATUS":"AWAL","RT":0,"RW":0,"TANGGAL":""},{"NO":"163","NO_PBP":"49111937224","KOTA":"KAB. PEMALANG","KECAMATAN":"BODEH","DESA":"KEBANDUNGAN","NAMA":"WARNINGSIH","NAMA_PENERIMA":"WARNINGSIH","NIK":"3327054203770003","NIK_PENERIMA":"3327054203770003","PEKERJAAN":"","FOTO_URL":"2PBP_49111937224.jpg","STATUS":"AWAL","RT":0,"RW":0,"TANGGAL":""},{"NO":"164","NO_PBP":"49111937374","KOTA":"KAB. PEMALANG","KECAMATAN":"BODEH","DESA":"KEBANDUNGAN","NAMA":"WARSONO","NAMA_PENERIMA":"FIFI HIDAYAH","NIK":"3326102108820002","NIK_PENERIMA":"3327054104960006","PEKERJAAN":"","FOTO_URL":"2PBP_49111937374.jpg","STATUS":"AWAL","RT":4,"RW":3,"TANGGAL":""},{"NO":"165","NO_PBP":"49111937301","KOTA":"KAB. PEMALANG","KECAMATAN":"BODEH","DESA":"KEBANDUNGAN","NAMA":"WASIAH","NAMA_PENERIMA":"WASIAH","NIK":"3327054107600269","NIK_PENERIMA":"3327054107600269","PEKERJAAN":"","FOTO_URL":"2PBP_49111937301.jpg","STATUS":"AWAL","RT":0,"RW":0,"TANGGAL":""},{"NO":"166","NO_PBP":"49111937323","KOTA":"KAB. PEMALANG","KECAMATAN":"BODEH","DESA":"KEBANDUNGAN","NAMA":"WASRI","NAMA_PENERIMA":"WASRI","NIK":"3327056401760003","NIK_PENERIMA":"3327056401760003","PEKERJAAN":"","FOTO_URL":"2PBP_49111937323.jpg","STATUS":"AWAL","RT":0,"RW":0,"TANGGAL":""},{"NO":"167","NO_PBP":"49111937226","KOTA":"KAB. PEMALANG","KECAMATAN":"BODEH","DESA":"KEBANDUNGAN","NAMA":"WIRYODIHARJO","NAMA_PENERIMA":"MARIPATUN","NIK":"3327052207890005","NIK_PENERIMA":"3327054701970008","PEKERJAAN":"","FOTO_URL":"2PBP_49111937226.jpg","STATUS":"AWAL","RT":0,"RW":0,"TANGGAL":""},{"NO":"168","NO_PBP":"49111937377","KOTA":"KAB. PEMALANG","KECAMATAN":"BODEH","DESA":"KEBANDUNGAN","NAMA":"YACHOBIT","NAMA_PENERIMA":"MUHIMATUL FAIZAH","NIK":"3327110607800003","NIK_PENERIMA":"3327057009890002","PEKERJAAN":"","FOTO_URL":"2PBP_49111937377.jpg","STATUS":"AWAL","RT":2,"RW":2,"TANGGAL":""},{"NO":"169","NO_PBP":"49111937285","KOTA":"KAB. PEMALANG","KECAMATAN":"BODEH","DESA":"KEBANDUNGAN","NAMA":"YENI SETIADI","NAMA_PENERIMA":"YENI SETIADI","NIK":"3327054212940008","NIK_PENERIMA":"3327054212940008","PEKERJAAN":"","FOTO_URL":"2PBP_49111937285.jpg","STATUS":"AWAL","RT":0,"RW":0,"TANGGAL":""},{"NO":"170","NO_PBP":"49111937375","KOTA":"KAB. PEMALANG","KECAMATAN":"BODEH","DESA":"KEBANDUNGAN","NAMA":"ZAENI","NAMA_PENERIMA":"ZAENI","NIK":"3326090604850008","NIK_PENERIMA":"3326090604850008","PEKERJAAN":"","FOTO_URL":"2PBP_49111937375.jpg","STATUS":"AWAL","RT":0,"RW":0,"TANGGAL":""},{"NO":"171","NO_PBP":"49111937381","KOTA":"KAB. PEMALANG","KECAMATAN":"BODEH","DESA":"KEBANDUNGAN","NAMA":"ZAENUDIN","NAMA_PENERIMA":"LUSIANAH","NIK":"3327050607730004","NIK_PENERIMA":"3327056009780003","PEKERJAAN":"","FOTO_URL":"2PBP_49111937381.jpg","STATUS":"AWAL","RT":1,"RW":2,"TANGGAL":""}]